<?xml version="1.0" encoding="UTF-8"?>
<!DOCTYPE mapper PUBLIC "-//mybatis.org//DTD Mapper 3.0//EN" "http://mybatis.org/dtd/mybatis-3-mapper.dtd">
<mapper namespace="com.lanjiao.gym.dao.OrderMapper">
  <resultMap id="BaseResultMap" type="com.lanjiao.gym.entity.Order">
    <!--
      WARNING - @mbg.generated
      This element is automatically generated by MyBatis Generator, do not modify.
    -->
    <id column="id" jdbcType="INTEGER" property="id" />
    <result column="order_id" jdbcType="VARCHAR" property="orderId" />
    <result column="user_id" jdbcType="VARCHAR" property="userId" />
  </resultMap>
  <sql id="Base_Column_List">
    <!--
      WARNING - @mbg.generated
      This element is automatically generated by MyBatis Generator, do not modify.
    -->
    id, order_id, user_id
  </sql>
  <select id="selectByPrimaryKey" parameterType="java.lang.Integer" resultMap="BaseResultMap">
    <!--
      WARNING - @mbg.generated
      This element is automatically generated by MyBatis Generator, do not modify.
    -->
    select 
    <include refid="Base_Column_List" />
    from order
    where id = #{id,jdbcType=INTEGER}
  </select>
  <delete id="deleteByPrimaryKey" parameterType="java.lang.Integer">
    <!--
      WARNING - @mbg.generated
      This element is automatically generated by MyBatis Generator, do not modify.
    -->
    delete from order
    where id = #{id,jdbcType=INTEGER}
  </delete>
  <insert id="insert" parameterType="com.lanjiao.gym.entity.Order">
    <!--
      WARNING - @mbg.generated
      This element is automatically generated by MyBatis Generator, do not modify.
    -->
    insert into order (id, order_id, user_id
      )
    values (#{id,jdbcType=INTEGER}, #{orderId,jdbcType=VARCHAR}, #{userId,jdbcType=VARCHAR}
      )
  </insert>
  <insert id="insertSelective" parameterType="com.lanjiao.gym.entity.Order">
    <!--
      WARNING - @mbg.generated
      This element is automatically generated by MyBatis Generator, do not modify.
    -->
    insert into order
    <trim prefix="(" suffix=")" suffixOverrides=",">
      <if test="id != null">
        id,
      </if>
      <if test="orderId != null">
        order_id,
      </if>
      <if test="userId != null">
        user_id,
      </if>
    </trim>
    <trim prefix="values (" suffix=")" suffixOverrides=",">
      <if test="id != null">
        #{id,jdbcType=INTEGER},
      </if>
      <if test="orderId != null">
        #{orderId,jdbcType=VARCHAR},
      </if>
      <if test="userId != null">
        #{userId,jdbcType=VARCHAR},
      </if>
    </trim>
  </insert>
  <update id="updateByPrimaryKeySelective" parameterType="com.lanjiao.gym.entity.Order">
    <!--
      WARNING - @mbg.generated
      This element is automatically generated by MyBatis Generator, do not modify.
    -->
    update order
    <set>
      <if test="orderId != null">
        order_id = #{orderId,jdbcType=VARCHAR},
      </if>
      <if test="userId != null">
        user_id = #{userId,jdbcType=VARCHAR},
      </if>
    </set>
    where id = #{id,jdbcType=INTEGER}
  </update>
  <update id="updateByPrimaryKey" parameterType="com.lanjiao.gym.entity.Order">
    <!--
      WARNING - @mbg.generated
      This element is automatically generated by MyBatis Generator, do not modify.
    -->
    update order
    set order_id = #{orderId,jdbcType=VARCHAR},
      user_id = #{userId,jdbcType=VARCHAR}
    where id = #{id,jdbcType=INTEGER}
  </update>
</mapper>